{
  "metadata" : {
    "realm" : "/bootcamp",
    "amsterVersion" : "6.5.2.3",
    "entityType" : "OTPEmailSender",
    "entityId" : "18f652a1-977c-432f-8894-29a92325225e",
    "pathParams" : { }
  },
  "data" : {
    "_id" : "18f652a1-977c-432f-8894-29a92325225e",
    "hostName" : "mail.example.com",
    "password" : null,
    "sslOption" : "SSL",
    "hostPort" : 25,
    "emailAttribute" : "mail",
    "smsGatewayImplementationClass" : "com.sun.identity.authentication.modules.hotp.DefaultSMSGatewayImpl",
    "fromEmailAddress" : "admin@example.com",
    "username" : "admin@example.com",
    "_type" : {
      "_id" : "OneTimePasswordSmtpSenderNode",
      "name" : "OTP Email Sender",
      "collection" : true
    }
  }
}